get_jsonnet_dependencies.py
get_jsonnet_dependencies-0.1.0.dist-info/entry_points.txt
get_jsonnet_dependencies-0.1.0.dist-info/LICENSE
get_jsonnet_dependencies-0.1.0.dist-info/WHEEL
get_jsonnet_dependencies-0.1.0.dist-info/METADATA
get_jsonnet_dependencies-0.1.0.dist-info/RECORD
